{"is":"system","title":"m.e. weather","permalink":"https://moeb98.github.io/moe-cstate/affected/m.e.-weather/","status":"ok","pages":[{"is":"issue","title":"m.e. weather down","createdAt":"2026-05-11 21:08:41 +0000 UTC","lastMod":"2026-05-11 23:19:43 +0200 +0200","permalink":"https://moeb98.github.io/moe-cstate/issues/2026-05-11_210841_m.e.weather/","severity":"down","resolved":true,"informational":false,"resolvedAt":"2026-05-11 21:18:41","affected":["m.e. weather"],"filename":"2026-05-11_21:08:41_m.e.weather.md"},{"is":"issue","title":"m.e. weather down","createdAt":"2026-05-11 20:59:41 +0000 UTC","lastMod":"2026-05-11 23:05:43 +0200 +0200","permalink":"https://moeb98.github.io/moe-cstate/issues/2026-05-11_205941_m.e.weather/","severity":"down","resolved":true,"informational":false,"resolvedAt":"2026-05-11 21:01:41","affected":["m.e. weather"],"filename":"2026-05-11_20:59:41_m.e.weather.md"}]}